[
    {
        "uuid": "C611DE1906CA4B35A510935D2DD9D04D",
        "actual": 1.3771110773086548,
        "predicted": -0.5389102697372437,
        "loss": 6.952481839543942,
        "climb_name": "Lille-skutt"
    },
    {
        "uuid": "69a9f9cf23c14c7ea658fa38934abbd9",
        "actual": 0.48144975304603577,
        "predicted": -1.2406573295593262,
        "loss": 6.248843853448448,
        "climb_name": "Bad dyno"
    },
    {
        "uuid": "25B518915A0F4AD6A0FA343FD937802A",
        "actual": 1.3771110773086548,
        "predicted": -0.2678007483482361,
        "loss": 5.968732870937397,
        "climb_name": "Poker Face"
    },
    {
        "uuid": "cafbaef6cb1e4573a87df0ca67f82913",
        "actual": 0.9637289643287659,
        "predicted": -0.5994558334350586,
        "loss": 5.672177888341562,
        "climb_name": "le bote"
    },
    {
        "uuid": "e50073a2ca8c44bab31c93e43f365068",
        "actual": 0.2747586667537689,
        "predicted": -1.1974084377288818,
        "loss": 5.341910764444334,
        "climb_name": "When we were younger"
    },
    {
        "uuid": "ca0484d54cf34bb9a20d6065e222c694",
        "actual": -1.378770112991333,
        "predicted": -2.8330135345458984,
        "loss": 5.276872825150293,
        "climb_name": "Centurion"
    },
    {
        "uuid": "75DE3F1D486B421DB26400C4F0B71FB2",
        "actual": -0.8275938034057617,
        "predicted": 0.6055686473846436,
        "loss": 5.200378340042519,
        "climb_name": "Spiderman Wannabe"
    },
    {
        "uuid": "e8224a2ffdf8465a936049dcfd01cc63",
        "actual": 1.5993727445602417,
        "predicted": 0.17042091488838196,
        "loss": 5.185099665352896,
        "climb_name": "Air Traffic Control"
    },
    {
        "uuid": "725228b4ec194734b03c706f9c504ca1",
        "actual": -2.2973878383636475,
        "predicted": -0.8825246095657349,
        "loss": 5.133977718370562,
        "climb_name": "wobbit*"
    },
    {
        "uuid": "B2F501F2423A4A11A74A928D79D7C657",
        "actual": -1.8380929231643677,
        "predicted": -0.4357347786426544,
        "loss": 5.088601725317933,
        "climb_name": "Doggie Arthritis"
    }
]